{
    "appKeys": {
        "chunk": 0,
        "incidents_req": 10,
        "incidents_size": 11,
        "index": 1,
        "message": 2,
        "size": 3,
        "traveltimes_req": 20,
        "traveltimes_size": 21,
        "webcam": 9
    },
    "capabilities": [
        ""
    ],
    "companyName": "YS",
    "longName": "Traffic Info Luxembourg",
    "projectType": "native",
    "resources": {
        "media": [
            {
                "file": "images/logo.png",
                "menuIcon": true,
                "name": "LOGO_IMAGE",
                "type": "png"
            }
        ]
    },
    "sdkVersion": "3",
    "shortName": "Traffic Info Luxembourg",
    "targetPlatforms": [
        "aplite",
        "basalt"
    ],
    "uuid": "9c6bb042-de52-4bee-a004-cd31a04f80a6",
    "versionLabel": "1.0",
    "watchapp": {
        "watchface": false
    }
}
